Workbook

Sheet Questions
A1: Question No. | B1: Practice Question | C1: Answers
A2: 01 | B2: Calculate the total transaction amount across all transaction records. | C2: =SUM(Transactions!I2:I1001) -> 29758389
A3: 02 | B3: Calculate the average transaction amount for successful transactions only. | C3: =AVERAGEIF(Transactions!L:L,"Successful",Transactions!I:I) -> 29906.663
A4: 03 | B4: Count the number of transactions that were reversed. | C4: =COUNTIF(Transactions!L:L,"Reversed") -> 127
A5: 04 | B5: Calculate total transaction fees collected from transactions made through the Mobile App that were successful. | C5: =SUMIFS(Transactions!J:J,Transactions!L:L,"Successful",Transactions!M:M,"Mobile App") -> 22270.6
A6: 05 | B6: Count transactions that were both international and made using UPI. | C6: =COUNTIFS(Transactions!N:N,"International",Transactions!K:K,"UPI") -> 89
A7: 06 | B7: Calculate the average transaction amount for international transactions made through the Website. | C7: =AVERAGEIFS(Transactions!I:I,Transactions!N:N,"International",Transactions!M:M,"Website") -> 29594.584
A8: 07 | B8: Add a column to Transactions that labels each transaction as 'High Value' when its amount is at least ₹25,000 and 'Standard' otherwise. | C8: Created
A9: 08 | B9: Add a column to Transactions showing the calendar month and year of each transaction. | C9: Created
A10: 09 | B10: Calculate the number of days between each customer's signup date and 9 October 2026. | C10: Done
A11: 10 | B11: Create a clean customer-name column that removes leading/trailing spaces and repeated spaces, if any. | C11: Already Cleaned
A12: 11 | B12: Add the merchant category to each transaction using its Merchant_ID. | C12: Created
A13: 12 | B13: Add each transaction customer's annual income to Transactions using Customer_ID. | C13: Created
A14: 13 | B14: For each transaction, return the merchant name; if the Merchant_ID cannot be found, display 'Not Found' instead of an error. | C14: Created
A15: 14 | B15: For each customer, calculate their total successful transaction amount. | C15: Created
A16: 15 | B16: Identify each customer's most recent transaction date. | C16: Created
A17: 16 | B17: Calculate the total loan amount for approved Business loans with a tenure of at least 36 months. | C17: =SUMIFS(Loans!F:F,Loans!I:I,"Approved",Loans!H:H,">=36",Loans!D:D,"Business") -> 1775575
A18: 17 | B18: Rank customers from highest to lowest by total successful transaction amount, with the highest total receiving rank 1. | C18: Created
A19: 18 | B19: Flag any repeated Customer_ID in the Customers sheet; mark the first occurrence 'First' and later occurrences 'Duplicate'. | C19: Created
A20: 19 | B20: Find the merchant category with the highest total successful transaction amount. | C20: Created
A21: 20 | B21: Calculate the approval rate for loan applications, defined as Approved applications divided by all loan applications. | C21: =COUNTIF(Loans!I:I,"Approved")/COUNTA(Loans!A:A) -> 0.31229236

Sheet Sheet1
A1: Transaction_Status | B1: Successful
H2: Row Labels | I2: Sum of Transaction_Amount | J2: Rank | L2: Transaction_Status | M2: Successful
A3: Row Labels | B3: Sum of Transaction_Amount | E3: Row Labels | F3: Max of Transaction_Timestamp | H3: CUST0001 | I3: 72623.73 | J3: =_xlfn.RANK.EQ(I3,I3:I175,0) -> 116
A4: CUST0001 | B4: 72623.73 | E4: CUST0001 | F4: 46243.834 | H4: CUST0002 | I4: 72564.79 | J4: =_xlfn.RANK.EQ(I4,I4:I176,0) -> 116 | L4: Row Labels | M4: Sum of Transaction_Amount
A5: CUST0002 | B5: 72564.79 | E5: CUST0002 | F5: 46048.313 | H5: CUST0003 | I5: 35661.4 | J5: =_xlfn.RANK.EQ(I5,I5:I177,0) -> 153 | L5: Electronics | M5: 1087629.8
A6: CUST0003 | B6: 35661.4 | E6: CUST0003 | F6: 45939.289 | H6: CUST0004 | I6: 123290.49 | J6: =_xlfn.RANK.EQ(I6,I6:I178,0) -> 59 | L6: Entertainment | M6: 1754421.2
A7: CUST0004 | B7: 123290.49 | E7: CUST0004 | F7: 46134.125 | H7: CUST0005 | I7: 88697.14 | J7: =_xlfn.RANK.EQ(I7,I7:I179,0) -> 103 | L7: Fashion | M7: 2423833.9
A8: CUST0005 | B8: 88697.14 | E8: CUST0005 | F8: 46172.028 | H8: CUST0006 | I8: 23670.3 | J8: =_xlfn.RANK.EQ(I8,I8:I180,0) -> 155 | L8: Food & Dining | M8: 1832364.5
A9: CUST0006 | B9: 23670.3 | E9: CUST0006 | F9: 46148.32 | H9: CUST0007 | I9: 88724.31 | J9: =_xlfn.RANK.EQ(I9,I9:I181,0) -> 102 | L9: Fuel | M9: 1053277.7
A10: CUST0007 | B10: 88724.31 | E10: CUST0007 | F10: 46257.829 | H10: CUST0008 | I10: 107785.56 | J10: =_xlfn.RANK.EQ(I10,I10:I182,0) -> 78 | L10: Grocery | M10: 1814236.2
A11: CUST0008 | B11: 107785.56 | E11: CUST0008 | F11: 45969.443 | H11: CUST0009 | I11: 57557.75 | J11: =_xlfn.RANK.EQ(I11,I11:I183,0) -> 124 | L11: Healthcare | M11: 3662592.1
A12: CUST0009 | B12: 57557.75 | E12: CUST0009 | F12: 46267.177 | H12: CUST0010 | I12: 69776.83 | J12: =_xlfn.RANK.EQ(I12,I12:I184,0) -> 114 | L12: Travel | M12: 2736808.1
A13: CUST0010 | B13: 69776.83 | E13: CUST0010 | F13: 46194.863 | H13: CUST0011 | I13: 66526.75 | J13: =_xlfn.RANK.EQ(I13,I13:I185,0) -> 114 | L13: Utilities | M13: 1698461.2
A14: CUST0011 | B14: 66526.75 | E14: CUST0011 | F14: 46157.851 | H14: CUST0012 | I14: 116642.73 | J14: =_xlfn.RANK.EQ(I14,I14:I186,0) -> 68 | L14: Grand Total | M14: 18063625
A15: CUST0012 | B15: 116642.73 | E15: CUST0012 | F15: 46263.226 | H15: CUST0013 | I15: 15659.41 | J15: =_xlfn.RANK.EQ(I15,I15:I187,0) -> 157
A16: CUST0013 | B16: 15659.41 | E16: CUST0013 | F16: 45913.103 | H16: CUST0014 | I16: 112003.43 | J16: =_xlfn.RANK.EQ(I16,I16:I188,0) -> 72
A17: CUST0014 | B17: 112003.43 | E17: CUST0014 | F17: 45905.843 | H17: CUST0015 | I17: 19173.6 | J17: =_xlfn.RANK.EQ(I17,I17:I189,0) -> 152
A18: CUST0015 | B18: 19173.6 | E18: CUST0015 | F18: 46274.802 | H18: CUST0016 | I18: 62797.29 | J18: =_xlfn.RANK.EQ(I18,I18:I190,0) -> 112
A19: CUST0016 | B19: 62797.29 | E19: CUST0016 | F19: 46291.513 | H19: CUST0017 | I19: 152600.75 | J19: =_xlfn.RANK.EQ(I19,I19:I191,0) -> 32
A20: CUST0017 | B20: 152600.75 | E20: CUST0017 | F20: 46246.081 | H20: CUST0018 | I20: 187082.61 | J20: =_xlfn.RANK.EQ(I20,I20:I192,0) -> 19
A21: CUST0018 | B21: 187082.61 | E21: CUST0018 | F21: 46260.881 | H21: CUST0019 | I21: 133864.4 | J21: =_xlfn.RANK.EQ(I21,I21:I193,0) -> 45
A22: CUST0019 | B22: 133864.4 | E22: CUST0019 | F22: 46298.934 | H22: CUST0020 | I22: 205617.86 | J22: =_xlfn.RANK.EQ(I22,I22:I194,0) -> 13
A23: CUST0020 | B23: 205617.86 | E23: CUST0020 | F23: 46254.049 | H23: CUST0021 | I23: 36777.38 | J23: =_xlfn.RANK.EQ(I23,I23:I195,0) -> 136
A24: CUST0021 | B24: 36777.38 | E24: CUST0021 | F24: 46089.958 | H24: CUST0022 | I24: 144273.41 | J24: =_xlfn.RANK.EQ(I24,I24:I196,0) -> 33
A25: CUST0022 | B25: 144273.41 | E25: CUST0022 | F25: 46285.232 | H25: CUST0023 | I25: 49413 | J25: =_xlfn.RANK.EQ(I25,I25:I197,0) -> 122
A26: CUST0023 | B26: 49413 | E26: CUST0023 | F26: 46173.748 | H26: CUST0024 | I26: 117934.53 | J26: =_xlfn.RANK.EQ(I26,I26:I198,0) -> 59
... A175: CUST0179 | B175: 105402.1 | E175: CUST0173 | F175: 46233.729 | H175: CUST0180 | I175: 223457.97 | J175: =_xlfn.RANK.EQ(I175,I175:I347,0) -> 1
A176: CUST0180 | B176: 223457.97 | E176: CUST0174 | F176: 46277.229
A177: Grand Total | B177: 18063625 | E177: CUST0175 | F177: 46193.416
E178: CUST0176 | F178: 46223.584
E179: CUST0177 | F179: 46238.793
E180: CUST0178 | F180: 46189.445
E181: CUST0179 | F181: 46147.052
E182: CUST0180 | F182: 46076.386
E183: Grand Total | F183: 46298.934

Sheet Transactions
A1: Transaction_ID | B1: Transaction_Timestamp | C1: month&year | D1: Customer_ID | E1: Annual Income | F1: Card_ID | G1: Merchant_ID | H1: Merchant Name | I1: Transaction_Amount | J1: Fee_Amount | K1: Payment_Method | L1: Transaction_Status | M1: Channel | N1: Transaction_Type | O1: Transaction_Purpose | P1: New column | Q1: Merchant Category
A2: TXN00001 | B2: 46017.926 | C2: =TEXT(B2,"mmm-yyyy") -> Dec-2025 | D2: CUST0053 | E2: =VLOOKUP(D2,Customers!A:H,7,0) -> Self-employed | F2: CARD0209 | G2: MER014 | H2: =IFERROR(VLOOKUP(Transactions!G2,Merchants!A:B,2,FALSE),"Not Found") -> Daily Stores | I2: 38002.96 | J2: 114.01 | K2: UPI | L2: Successful | M2: POS | N2: International | O2: Bill Payment | P2: =IF(I2>=2500,"High Value","Standard") -> High Value | Q2: =VLOOKUP(G2,Merchants!A:C,3,TRUE) -> Travel
A3: TXN00002 | B3: 45989.444 | C3: =TEXT(B3,"mmm-yyyy") -> Nov-2025 | D3: CUST0035 | E3: =VLOOKUP(D3,Customers!A:H,7,0) -> Student | F3: CARD0247 | G3: MER027 | H3: =IFERROR(VLOOKUP(Transactions!G3,Merchants!A:B,2,FALSE),"Not Found") -> Prime Digital | I3: 17431.06 | J3: 34.86 | K3: UPI | L3: Successful | M3: POS | N3: Domestic | O3: Bill Payment | P3: =IF(I3>=2500,"High Value","Standard") -> High Value | Q3: =VLOOKUP(G3,Merchants!A:C,3,TRUE) -> Fuel
A4: TXN00003 | B4: 45913.222 | C4: =TEXT(B4,"mmm-yyyy") -> Sep-2025 | D4: CUST0126 | E4: =VLOOKUP(D4,Customers!A:H,7,0) -> Self-employed | F4: CARD0037 | G4: MER037 | H4: =IFERROR(VLOOKUP(Transactions!G4,Merchants!A:B,2,FALSE),"Not Found") -> Metro Pay | I4: 42712.55 | J4: 427.13 | K4: Debit Card | L4: Reversed | M4: Branch | N4: International | O4: Cash Withdrawal | P4: =IF(I4>=2500,"High Value","Standard") -> High Value | Q4: =VLOOKUP(G4,Merchants!A:C,3,TRUE) -> Fashion
A5: TXN00004 | B5: 45735.961 | C5: =TEXT(B5,"mmm-yyyy") -> Mar-2025 | D5: CUST0132 | E5: =VLOOKUP(D5,Customers!A:H,7,0) -> Student | F5: CARD0192 | G5: MER018 | H5: =IFERROR(VLOOKUP(Transactions!G5,Merchants!A:B,2,FALSE),"Not Found") -> Nova Retail | I5: 47696.46 | J5: 476.96 | K5: Debit Card | L5: Failed | M5: Branch | N5: International | O5: Transfer | P5: =IF(I5>=2500,"High Value","Standard") -> High Value | Q5: =VLOOKUP(G5,Merchants!A:C,3,TRUE) -> Grocery
A6: TXN00005 | B6: 46253.004 | C6: =TEXT(B6,"mmm-yyyy") -> Aug-2026 | D6: CUST0118 | E6: =VLOOKUP(D6,Customers!A:H,7,0) -> Business Owner | F6: CARD0163 | G6: MER043 | H6: =IFERROR(VLOOKUP(Transactions!G6,Merchants!A:B,2,FALSE),"Not Found") -> Metro Pay | I6: 52147.57 | J6: 104.3 | K6: Debit Card | L6: Reversed | M6: Mobile App | N6: International | O6: Bill Payment | P6: =IF(I6>=2500,"High Value","Standard") -> High Value | Q6: =VLOOKUP(G6,Merchants!A:C,3,TRUE) -> Travel
A7: TXN00006 | B7: 46097.321 | C7: =TEXT(B7,"mmm-yyyy") -> Mar-2026 | D7: CUST0087 | E7: =VLOOKUP(D7,Customers!A:H,7,0) -> Salaried | F7: CARD0141 | G7: MER037 | H7: =IFERROR(VLOOKUP(Transactions!G7,Merchants!A:B,2,FALSE),"Not Found") -> Metro Pay | I7: 29733.43 | J7: 148.67 | K7: Credit Card | L7: Successful | M7: Branch | N7: International | O7: Retail Purchase | P7: =IF(I7>=2500,"High Value","Standard") -> High Value | Q7: =VLOOKUP(G7,Merchants!A:C,3,TRUE) -> Fashion
A8: TXN00007 | B8: 45705.151 | C8: =TEXT(B8,"mmm-yyyy") -> Feb-2025 | D8: CUST0032 | E8: =VLOOKUP(D8,Customers!A:H,7,0) -> Student | F8: CARD0238 | G8: MER011 | H8: =IFERROR(VLOOKUP(Transactions!G8,Merchants!A:B,2,FALSE),"Not Found") -> Quick Pay | I8: 37608.15 | J8: 75.22 | K8: Net Banking | L8: Reversed | M8: Branch | N8: Domestic | O8: Cash Withdrawal | P8: =IF(I8>=2500,"High Value","Standard") -> High Value | Q8: =VLOOKUP(G8,Merchants!A:C,3,TRUE) -> Healthcare
A9: TXN00008 | B9: 45865.2 | C9: =TEXT(B9,"mmm-yyyy") -> Jul-2025 | D9: CUST0024 | E9: =VLOOKUP(D9,Customers!A:H,7,0) -> Self-employed | F9: CARD0168 | G9: MER024 | H9: =IFERROR(VLOOKUP(Transactions!G9,Merchants!A:B,2,FALSE),"Not Found") -> Metro Stores | I9: 52940.65 | J9: 264.7 | K9: Debit Card | L9: Successful | M9: Mobile App | N9: International | O9: Bill Payment | P9: =IF(I9>=2500,"High Value","Standard") -> High Value | Q9: =VLOOKUP(G9,Merchants!A:C,3,TRUE) -> Healthcare
A10: TXN00009 | B10: 45711.601 | C10: =TEXT(B10,"mmm-yyyy") -> Feb-2025 | D10: CUST0110 | E10: =VLOOKUP(D10,Customers!A:H,7,0) -> Business Owner | F10: CARD0168 | G10: MER006 | H10: =IFERROR(VLOOKUP(Transactions!G10,Merchants!A:B,2,FALSE),"Not Found") -> Nova Pay | I10: 37573.7 | J10: 112.72 | K10: UPI | L10: Failed | M10: Mobile App | N10: Domestic | O10: Cash Withdrawal | P10: =IF(I10>=2500,"High Value","Standard") -> High Value | Q10: =VLOOKUP(G10,Merchants!A:C,3,TRUE) -> Fashion
A11: TXN00010 | B11: 45737.201 | C11: =TEXT(B11,"mmm-yyyy") -> Mar-2025 | D11: CUST0003 | E11: =VLOOKUP(D11,Customers!A:H,7,0) -> Student | F11: CARD0003 | G11: MER045 | H11: =IFERROR(VLOOKUP(Transactions!G11,Merchants!A:B,2,FALSE),"Not Found") -> Blue Services | I11: 35661.4 | J11: 356.61 | K11: Debit Card | L11: Successful | M11: Mobile App | N11: International | O11: Bill Payment | P11: =IF(I11>=2500,"High Value","Standard") -> High Value | Q11: =VLOOKUP(G11,Merchants!A:C,3,TRUE) -> Travel
A12: TXN00011 | B12: 46147.107 | C12: =TEXT(B12,"mmm-yyyy") -> May-2026 | D12: CUST0027 | E12: =VLOOKUP(D12,Customers!A:H,7,0) -> Salaried | F12: CARD0081 | G12: MER024 | H12: =IFERROR(VLOOKUP(Transactions!G12,Merchants!A:B,2,FALSE),"Not Found") -> Metro Stores | I12: 13813.92 | J12: 27.63 | K12: Debit Card | L12: Successful | M12: Website | N12: International | O12: Bill Payment | P12: =IF(I12>=2500,"High Value","Standard") -> High Value | Q12: =VLOOKUP(G12,Merchants!A:C,3,TRUE) -> Healthcare
A13: TXN00012 | B13: 45804.104 | C13: =TEXT(B13,"mmm-yyyy") -> May-2025 | D13: CUST0113 | E13: =VLOOKUP(D13,Customers!A:H,7,0) -> Business Owner | F13: CARD0090 | G13: MER014 | H13: =IFERROR(VLOOKUP(Transactions!G13,Merchants!A:B,2,FALSE),"Not Found") -> Daily Stores | I13: 31877.45 | J13: 95.63 | K13: Credit Card | L13: Successful | M13: Branch | N13: International | O13: Bill Payment | P13: =IF(I13>=2500,"High Value","Standard") -> High Value | Q13: =VLOOKUP(G13,Merchants!A:C,3,TRUE) -> Travel
... A1001: TXN01000 | B1001: 46278.1 | C1001: =TEXT(B1001,"mmm-yyyy") -> Sep-2026 | D1001: CUST0116 | E1001: =VLOOKUP(D1001,Customers!A:H,7,0) -> Business Owner | F1001: CARD0092 | G1001: MER031 | H1001: =IFERROR(VLOOKUP(Transactions!G1001,Merchants!A:B,2,FALSE),"Not Found") -> Daily Digital | I1001: 34195.15 | J1001: 170.98 | K1001: Debit Card | L1001: Failed | M1001: Branch | N1001: International | O1001: Cash Withdrawal | P1001: =IF(I1001>=2500,"High Value","Standard") -> High Value | Q1001: =VLOOKUP(G1001,Merchants!A:C,3,TRUE) -> Grocery

Sheet Customers
A1: Customer_ID | B1: Repeated check | C1: Customer_Name | D1: City | E1: Region | F1: DOB | G1: Employment_Type | H1: Annual_Income | I1: Income_Band | J1: Risk_Band | K1: Customer_Since | L1: daysdiff
A2: CUST0001 | B2: =IF(COUNTIF(A2:A181,A2)=1,"First","Duplicate") -> First | C2: Aanya Gupta | D2: Delhi | E2: North | F2: 33850 | G2: Salaried | H2: 284902 | I2: Below 5L | J2: High | K2: 44834 | L2: =DATE(2026,10,9)-K2 -> 1470
A3: CUST0002 | B3: =IF(COUNTIF(A3:A182,A3)=1,"First","Duplicate") -> First | C3: Aarav Verma | D3: Lucknow | E3: North | F3: 38663 | G3: Self-employed | H3: 544647 | I3: 5L-10L | J3: Low | K3: 43961 | L3: =DATE(2026,10,9)-K3 -> 2343
A4: CUST0003 | B4: =IF(COUNTIF(A4:A183,A4)=1,"First","Duplicate") -> First | C4: Reyansh Mehta | D4: Lucknow | E4: North | F4: 25707 | G4: Student | H4: 2705049 | I4: 20L+ | J4: Low | K4: 46129 | L4: =DATE(2026,10,9)-K4 -> 175
A5: CUST0004 | B5: =IF(COUNTIF(A5:A184,A5)=1,"First","Duplicate") -> First | C5: Sai Mehta | D5: Jaipur | E5: North | F5: 33953 | G5: Student | H5: 2651559 | I5: 20L+ | J5: Medium | K5: 43857 | L5: =DATE(2026,10,9)-K5 -> 2447
A6: CUST0005 | B6: =IF(COUNTIF(A6:A185,A6)=1,"First","Duplicate") -> First | C6: Vihaan Verma | D6: Pune | E6: West | F6: 31893 | G6: Student | H6: 832128 | I6: 5L-10L | J6: Low | K6: 45209 | L6: =DATE(2026,10,9)-K6 -> 1095
A7: CUST0006 | B7: =IF(COUNTIF(A7:A186,A7)=1,"First","Duplicate") -> First | C7: Riya Das | D7: Chennai | E7: South | F7: 33505 | G7: Salaried | H7: 1622654 | I7: 10L-20L | J7: Medium | K7: 44008 | L7: =DATE(2026,10,9)-K7 -> 2296
A8: CUST0007 | B8: =IF(COUNTIF(A8:A187,A8)=1,"First","Duplicate") -> First | C8: Navya Singh | D8: Delhi | E8: North | F8: 34444 | G8: Salaried | H8: 2495426 | I8: 20L+ | J8: Low | K8: 45312 | L8: =DATE(2026,10,9)-K8 -> 992
A9: CUST0008 | B9: =IF(COUNTIF(A9:A188,A9)=1,"First","Duplicate") -> First | C9: Aanya Roy | D9: Hyderabad | E9: South | F9: 34320 | G9: Salaried | H9: 3422483 | I9: 20L+ | J9: Medium | K9: 44157 | L9: =DATE(2026,10,9)-K9 -> 2147
A10: CUST0009 | B10: =IF(COUNTIF(A10:A189,A10)=1,"First","Duplicate") -> First | C10: Myra Patel | D10: Pune | E10: West | F10: 36792 | G10: Self-employed | H10: 2081740 | I10: 20L+ | J10: High | K10: 44497 | L10: =DATE(2026,10,9)-K10 -> 1807
A11: CUST0010 | B11: =IF(COUNTIF(A11:A190,A11)=1,"First","Duplicate") -> First | C11: Ishaan Mehta | D11: Pune | E11: West | F11: 27177 | G11: Self-employed | H11: 3123647 | I11: 20L+ | J11: Low | K11: 44531 | L11: =DATE(2026,10,9)-K11 -> 1773
A12: CUST0011 | B12: =IF(COUNTIF(A12:A191,A12)=1,"First","Duplicate") -> First | C12: Aanya Joshi | D12: Jaipur | E12: North | F12: 33683 | G12: Business Owner | H12: 1771551 | I12: 10L-20L | J12: Low | K12: 46112 | L12: =DATE(2026,10,9)-K12 -> 192
A13: CUST0012 | B13: =IF(COUNTIF(A13:A192,A13)=1,"First","Duplicate") -> First | C13: Diya Verma | D13: Hyderabad | E13: South | F13: 35174 | G13: Self-employed | H13: 314638 | I13: Below 5L | J13: High | K13: 45474 | L13: =DATE(2026,10,9)-K13 -> 830
... A181: CUST0180 | B181: =IF(COUNTIF(A181:A360,A181)=1,"First","Duplicate") -> First | C181: Arjun Joshi | D181: Delhi | E181: North | F181: 41464 | G181: Student | H181: 2603965 | I181: 20L+ | J181: Low | K181: 44702 | L181: =DATE(2026,10,9)-K181 -> 1602

Sheet Merchants
A1: Merchant_ID | B1: Merchant_Name | C1: Merchant_Category | D1: City | E1: Operating_Model
A2: MER001 | B2: Urban Services | C2: Fashion | D2: Chennai | E2: Online
A3: MER002 | B3: Daily Stores | C3: Entertainment | D3: Lucknow | E3: Omnichannel
A4: MER003 | B4: Fresh Mart | C4: Electronics | D4: Mumbai | E4: Online
A5: MER004 | B5: Daily Digital | C5: Healthcare | D5: Chennai | E5: Online
A6: MER005 | B6: Prime Foods | C6: Entertainment | D6: Delhi | E6: Online
A7: MER006 | B7: Nova Pay | C7: Fashion | D7: Hyderabad | E7: Offline
A8: MER007 | B8: Blue Hub | C8: Healthcare | D8: Bengaluru | E8: Offline
A9: MER008 | B9: Daily Services | C9: Food & Dining | D9: Mumbai | E9: Online
A10: MER009 | B10: Prime Mart | C10: Food & Dining | D10: Pune | E10: Offline
A11: MER010 | B11: Blue Hub | C11: Utilities | D11: Kolkata | E11: Offline
A12: MER011 | B12: Quick Pay | C12: Healthcare | D12: Kolkata | E12: Online
... A46: MER045 | B46: Blue Services | C46: Travel | D46: Lucknow | E46: Online

Sheet Loans
A1: Loan_ID | B1: Customer_ID | C1: Application_Date | D1: Loan_Type | E1: Loan_Purpose | F1: Loan_Amount | G1: Interest_Rate | H1: Tenure_Months | I1: Loan_Status | J1: Application_Channel
A2: LOAN0001 | B2: CUST0049 | C2: 45612 | D2: Business | E2: Home Improvement | F2: 821156 | G2: 10.55 | H2: 48 | I2: Rejected | J2: Partner
A3: LOAN0002 | B3: CUST0119 | C3: 45624 | D3: Vehicle | E3: Travel | F3: 462829 | G3: 10.33 | H3: 60 | I3: Rejected | J3: Mobile App
A4: LOAN0003 | B4: CUST0098 | C4: 46186 | D4: Business | E4: Travel | F4: 300000 | G4: 12.89 | H4: 60 | I4: Closed | J4: Website
A5: LOAN0004 | B5: CUST0056 | C5: 45446 | D5: Personal | E5: Medical | F5: 232843 | G5: 13.2 | H5: 18 | I5: Approved | J5: Website
A6: LOAN0005 | B6: CUST0078 | C6: 45314 | D6: Home | E6: Expansion | F6: 206006 | G6: 11.23 | H6: 84 | I6: Under Review | J6: Partner
A7: LOAN0006 | B7: CUST0125 | C7: 45735 | D7: Personal | E7: Expansion | F7: 100000 | G7: 20.04 | H7: 12 | I7: Closed | J7: Partner
A8: LOAN0007 | B8: CUST0133 | C8: 45914 | D8: Vehicle | E8: Working Capital | F8: 150000 | G8: 11.1 | H8: 84 | I8: Approved | J8: Branch
A9: LOAN0008 | B9: CUST0176 | C9: 45938 | D9: Home | E9: Travel | F9: 200000 | G9: 15.84 | H9: 18 | I9: Rejected | J9: Branch
A10: LOAN0009 | B10: CUST0095 | C10: 46034 | D10: Home | E10: Travel | F10: 100000 | G10: 9.26 | H10: 84 | I10: Rejected | J10: Website
A11: LOAN0010 | B11: CUST0060 | C11: 45506 | D11: Education | E11: Debt Consolidation | F11: 761715 | G11: 19.49 | H11: 84 | I11: Closed | J11: Branch
A12: LOAN0011 | B12: CUST0050 | C12: 45883 | D12: Business | E12: Expansion | F12: 772251 | G12: 17.88 | H12: 24 | I12: Defaulted | J12: Website
A13: LOAN0012 | B13: CUST0145 | C13: 46124 | D13: Vehicle | E13: Medical | F13: 552321 | G13: 12.26 | H13: 12 | I13: Rejected | J13: Website
... A301: LOAN0300 | B301: CUST0117 | C301: 45704 | D301: Vehicle | E301: Debt Consolidation | F301: 164775 | G301: 9.23 | H301: 84 | I301: Approved | J301: Partner

Sheet Cards
A1: Card_ID | B1: Customer_ID | C1: Card_Type | D1: Issue_Date | E1: Card_Status | F1: Network | G1: Card_Tier
A2: CARD0001 | B2: CUST0131 | C2: Debit | D2: 45931 | E2: Active | F2: Mastercard | G2: Classic
A3: CARD0002 | B3: CUST0088 | C3: Debit | D3: 45074 | E3: Active | F3: Visa | G3: Classic
A4: CARD0003 | B4: CUST0076 | C4: Credit | D4: 44513 | E4: Active | F4: RuPay | G4: Platinum
A5: CARD0004 | B5: CUST0170 | C5: Debit | D5: 44351 | E5: Closed | F5: RuPay | G5: Classic
A6: CARD0005 | B6: CUST0040 | C6: Credit | D6: 45740 | E6: Active | F6: RuPay | G6: Platinum
A7: CARD0006 | B7: CUST0113 | C7: Credit | D7: 44875 | E7: Active | F7: RuPay | G7: Platinum
A8: CARD0007 | B8: CUST0114 | C8: Prepaid | D8: 45169 | E8: Active | F8: RuPay | G8: Gold
A9: CARD0008 | B9: CUST0137 | C9: Credit | D9: 45155 | E9: Active | F9: Mastercard | G9: Classic
A10: CARD0009 | B10: CUST0174 | C10: Prepaid | D10: 45703 | E10: Closed | F10: Mastercard | G10: Gold
A11: CARD0010 | B11: CUST0129 | C11: Prepaid | D11: 45761 | E11: Active | F11: Visa | G11: Classic
A12: CARD0011 | B12: CUST0065 | C12: Credit | D12: 44763 | E12: Active | F12: Mastercard | G12: Platinum
A13: CARD0012 | B13: CUST0133 | C13: Credit | D13: 44617 | E13: Active | F13: Visa | G13: Gold
... A251: CARD0250 | B251: CUST0061 | C251: Credit | D251: 44677 | E251: Blocked | F251: RuPay | G251: Platinum
